slsmanager/__init__.py
slsmanager/manager.py
slsmanager-0.2.2.dist-info/LICENSE
slsmanager-0.2.2.dist-info/METADATA
slsmanager-0.2.2.dist-info/WHEEL
slsmanager-0.2.2.dist-info/entry_points.txt
slsmanager-0.2.2.dist-info/top_level.txt
slsmanager-0.2.2.dist-info/RECORD
