Metadata-Version: 2.1
Name: slsmanager
Version: 0.2.2
Summary: A basic tool that simplifies the deployment of AWS lambda functions
Home-page: https://github.com/AineshSootha/serverlessManager
Author: Ainesh Sootha
Author-email: aineshsootha@gmail.com
License: UNKNOWN
Project-URL: Bug Tracker, https://github.com/AineshSootha/serverlessManager/issues
Platform: UNKNOWN
Classifier: Programming Language :: Python :: 3
Classifier: License :: OSI Approved :: MIT License
Classifier: Operating System :: OS Independent
Requires-Python: >=3.6
License-File: LICENSE
Requires-Dist: click
Requires-Dist: pathlib
Requires-Dist: colorama
Requires-Dist: boto3
Requires-Dist: progress
Requires-Dist: glob2
Requires-Dist: pyyaml
